phytreeviz/__init__.py
phytreeviz/scripts/__init__.py
phytreeviz/scripts/cli.py
phytreeviz/treeviz.py
phytreeviz/utils/__init__.py
phytreeviz/utils/example_data/large_example.nwk
phytreeviz/utils/example_data/medium_example.nwk
phytreeviz/utils/example_data/small_example.nwk
phytreeviz-0.2.0.dist-info/LICENSE
phytreeviz-0.2.0.dist-info/METADATA
phytreeviz-0.2.0.dist-info/WHEEL
phytreeviz-0.2.0.dist-info/entry_points.txt
phytreeviz-0.2.0.dist-info/RECORD
