Metadata-Version: 2.1
Name: phytreeviz
Version: 0.2.0
Summary: Simple phylogenetic tree visualization python package
Home-page: https://github.com/moshi4/phyTreeViz/
License: MIT
Keywords: bioinformatics,phylogenetics,visualization,matplotlib,phylogenetic-tree
Author: moshi4
Requires-Python: >=3.8,<4.0
Classifier: Framework :: Matplotlib
Classifier: Intended Audience :: Science/Research
Classifier: License :: OSI Approved :: MIT License
Classifier: Programming Language :: Python :: 3
Classifier: Programming Language :: Python :: 3.8
Classifier: Programming Language :: Python :: 3.9
Classifier: Programming Language :: Python :: 3.10
Classifier: Programming Language :: Python :: 3.11
Classifier: Programming Language :: Python :: 3.12
Classifier: Topic :: Scientific/Engineering :: Bio-Informatics
Requires-Dist: biopython (>=1.7.9)
Requires-Dist: matplotlib (>=3.5.3)
Requires-Dist: numpy (>=1.21.1)
Project-URL: Repository, https://github.com/moshi4/phyTreeViz/
